{
  "name": "FileObject",
  "schema": {
    "type": "object",
    "required": [
      "@id",
      "@type",
      "@context"
    ],
    "properties": {
      "@id": {
        "type": "string",
        "cordra": {
          "disableInUi": true,
          "type": {
            "autoGeneratedField": "handle"
          },
          "preview": {
            "showInPreview": true,
            "isPrimary": true
          }
        }
      },
      "@type": {
        "type": "string",
        "cordra": {
          "disableInUi": true
        }
      },
      "@context": {
        "type": "string",
        "cordra": {
          "disableInUi": true
        }
      },
      "name": {
        "type": "string",
        "cordra": {
          "preview": {
            "showInPreview": true
          }
        }
      },
      "description": {
        "type": "string",
        "cordra": {
          "preview": {
            "showInPreview": true
          }
        }
      },
      "contentSize": {
        "type": "integer",
        "cordra": {
          "preview": {
            "showInPreview": true
          }
        }
      },
      "encodingFormat": {
        "type": "string",
        "cordra": {
          "preview": {
            "showInPreview": true
          }
        }
      }
    }
  }
}