{
  "name": "FormalParameter",
  "schema": {
    "type": "object",
    "required": [
      "@context",
      "@id",
      "@type",
      "name",
      "additionalType"
    ],
    "properties": {
      "@context": {
        "type": "array",
        "items": {
          "oneOf": [{"type": "string"}, {"type": "object"}]
        },
        "default": [
          "https://schema.org/",
          {"FormalParameter":  "https://bioschemas.org/FormalParameter"}
        ],
        "cordra": {
          "disableInUi": true
        }
      },
      "@id": {
        "type": "string",
        "cordra": {
          "disableInUi": true,
          "type": {
            "autoGeneratedField": "handle"
          }
        }
      },
      "@type": {
        "type": "array",
        "items": {
          "type": "string"
        },
        "default": [
          "PropertyValue"
        ]
      },
      "name": {
        "type": "string"
      },
      "description": {
        "type": "string"
      },
      "additionalType": {
        "type": "string"
      }
    }
  }
}